Workbook

Sheet Income_Statement
A1: Societe Generale Ghana PLC — Income Statement
A2: Statement of Profit or Loss and Other Comprehensive Income | For the quarter ended 31 March
A3: All amounts in thousands of Ghana Cedis (GH¢'000) unless stated otherwise
A4: Line Item | B4: Q1 2026 (GH¢'000) | C4: Q1 2025 (GH¢'000) | D4: GH¢ Variance | E4: % Variance
A5: Interest income | B5: 278778 | C5: 365242 | D5: =B5-C5 -> -86464 | E5: =IF(C5<>0,(B5-C5)/ABS(C5),"N/A") -> -0.23673072
A6: Interest expense | B6: -53968 | C6: -60226 | D6: =B6-C6 -> 6258 | E6: =IF(C6<>0,(B6-C6)/ABS(C6),"N/A") -> 0.10390861
A7: Net interest income | B7: 224810 | C7: 305016 | D7: =B7-C7 -> -80206 | E7: =IF(C7<>0,(B7-C7)/ABS(C7),"N/A") -> -0.2629567
A9: Fees and commission income | B9: 41053 | C9: 42392 | D9: =B9-C9 -> -1339 | E9: =IF(C9<>0,(B9-C9)/ABS(C9),"N/A") -> -0.031586148
A10: Fees and commission expense | B10: -16229 | C10: -18988 | D10: =B10-C10 -> 2759 | E10: =IF(C10<>0,(B10-C10)/ABS(C10),"N/A") -> 0.1453023
A11: Net fees and commission income | B11: 24824 | C11: 23404 | D11: =B11-C11 -> 1420 | E11: =IF(C11<>0,(B11-C11)/ABS(C11),"N/A") -> 0.060673389
A13: Net trading revenue | B13: 22064 | C13: 15914 | D13: =B13-C13 -> 6150 | E13: =IF(C13<>0,(B13-C13)/ABS(C13),"N/A") -> 0.38645218
A14: Net income from other financial instruments at fair value | B14: 1698 | C14: 5358 | D14: =B14-C14 -> -3660 | E14: =IF(C14<>0,(B14-C14)/ABS(C14),"N/A") -> -0.68309071
A15: Other operating income | B15: 2119 | C15: -2198 | D15: =B15-C15 -> 4317 | E15: =IF(C15<>0,(B15-C15)/ABS(C15),"N/A") -> 1.9640582
A16: Total other operating income | B16: 25881 | C16: 19074 | D16: =B16-C16 -> 6807 | E16: =IF(C16<>0,(B16-C16)/ABS(C16),"N/A") -> 0.35687323
A18: Operating income | B18: 275515 | C18: 347494 | D18: =B18-C18 -> -71979 | E18: =IF(C18<>0,(B18-C18)/ABS(C18),"N/A") -> -0.20713739
A20: Net impairment loss on financial assets | B20: -21167 | C20: 28942 | D20: =B20-C20 -> -50109 | E20: =IF(C20<>0,(B20-C20)/ABS(C20),"N/A") -> -1.7313593
... A33: Total comprehensive income for the period | B33: 51685 | C33: 136617 | D33: =B33-C33 -> -84932 | E33: =IF(C33<>0,(B33-C33)/ABS(C33),"N/A") -> -0.62167959
A35: Basic and diluted earnings per share (GH¢) | B35: 0.29 | C35: 0.77 | D35: =B35-C35 -> -0.48 | E35: =(B35-C35)/ABS(C35) -> -0.62337662

Sheet Sheet1
A1: Build the Waterfall Chart (Profit Bridge)
A2: Driver | B2: GH¢ Impact on PBT
A3: Starting PBT (Q1 2025) | B3: 212611
A4: Net Interest Income | B4: -80206
A5: Net Fees & Commission | B5: 1420
A6: Total Other Op. Income | B6: 6807
A7: Impairment (net swing) | B7: -50109
A8: Personnel Expense | B8: -3986
A9: Depreciation & Amort. | B9: -9754
A10: Other Operating Exp. | B10: 1540
A11: Total PBT Q1 2026 | B11: =SUM(B3:B10) -> 78323
B27: Q1 2025 | C27: Q1 2026
A28: Operating income | B28: 347494 | C28: 275515
A29: Total operating expenses | B29: 163825 | C29: 176025

Sheet Balance_Sheet
A1: Societe Generale Ghana PLC — Balance Sheet
A2: Statement of Financial Position | As at 31 March
A3: All amounts in thousands of Ghana Cedis (GH¢'000) unless stated otherwise
A4: Line Item | B4: 2026 (GH¢'000) | C4: 2025 (GH¢'000) | D4: GH¢ Variance | E4: % Variance
A5: ASSETS
A6: Cash and cash equivalents | B6: 2773720 | C6: 3293772 | D6: =B6-C6 -> -520052 | E6: =IF(C6<>0,(B6-C6)/ABS(C6),"N/A") -> -0.1578895
A7: Non-pledged trading assets | B7: 7587 | C7: 10369 | D7: =B7-C7 -> -2782 | E7: =IF(C7<>0,(B7-C7)/ABS(C7),"N/A") -> -0.26829974
A8: Debt instruments at amortised cost | B8: 2615737 | C8: 1396566 | D8: =B8-C8 -> 1219171 | E8: =IF(C8<>0,(B8-C8)/ABS(C8),"N/A") -> 0.87297772
A9: Loans and advances to customers | B9: 4183532 | C9: 4817070 | D9: =B9-C9 -> -633538 | E9: =IF(C9<>0,(B9-C9)/ABS(C9),"N/A") -> -0.13151937
A10: Equity investments | B10: 9368 | C10: 5513 | D10: =B10-C10 -> 3855 | E10: =IF(C10<>0,(B10-C10)/ABS(C10),"N/A") -> 0.6992563
A11: Deferred tax assets | B11: 2771 | C11: 0 | D11: =B11-C11 -> 2771 | E11: =IF(C11<>0,(B11-C11)/ABS(C11),"N/A") -> N/A
A12: Current tax assets | B12: 28741 | C12: 0 | D12: =B12-C12 -> 28741 | E12: =IF(C12<>0,(B12-C12)/ABS(C12),"N/A") -> N/A
A13: Property, plant and equipment | B13: 716454 | C13: 752321 | D13: =B13-C13 -> -35867 | E13: =IF(C13<>0,(B13-C13)/ABS(C13),"N/A") -> -0.047675128
A14: Intangible assets | B14: 167659 | C14: 152175 | D14: =B14-C14 -> 15484 | E14: =IF(C14<>0,(B14-C14)/ABS(C14),"N/A") -> 0.10175127
A15: Other assets | B15: 118112 | C15: 143083 | D15: =B15-C15 -> -24971 | E15: =IF(C15<>0,(B15-C15)/ABS(C15),"N/A") -> -0.17452108
A16: Total assets | B16: 10623681 | C16: 10570869 | D16: =B16-C16 -> 52812 | E16: =IF(C16<>0,(B16-C16)/ABS(C16),"N/A") -> 0.0049959942
A18: LIABILITIES
A19: Derivative financial liabilities | B19: 0 | C19: 3410 | D19: =B19-C19 -> -3410 | E19: =IF(C19<>0,(B19-C19)/ABS(C19),"N/A") -> -1
A20: Deposits from banks | B20: 1553 | C20: 60381 | D20: =B20-C20 -> -58828 | E20: =IF(C20<>0,(B20-C20)/ABS(C20),"N/A") -> -0.97427999
A21: Deposits from customers | B21: 6666855 | C21: 6443855 | D21: =B21-C21 -> 223000 | E21: =IF(C21<>0,(B21-C21)/ABS(C21),"N/A") -> 0.034606614
A22: Borrowings | B22: 336454 | C22: 428952 | D22: =B22-C22 -> -92498 | E22: =IF(C22<>0,(B22-C22)/ABS(C22),"N/A") -> -0.21563718
A23: Current tax liabilities | B23: 0 | C23: 24937 | D23: =B23-C23 -> -24937 | E23: =IF(C23<>0,(B23-C23)/ABS(C23),"N/A") -> -1
A24: Deferred tax liabilities | B24: 0 | C24: 2218 | D24: =B24-C24 -> -2218 | E24: =IF(C24<>0,(B24-C24)/ABS(C24),"N/A") -> -1
A25: Other liabilities | B25: 965359 | C25: 1024617 | D25: =B25-C25 -> -59258 | E25: =IF(C25<>0,(B25-C25)/ABS(C25),"N/A") -> -0.057834293
A26: Total liabilities | B26: 7970221 | C26: 7988370 | D26: =B26-C26 -> -18149 | E26: =IF(C26<>0,(B26-C26)/ABS(C26),"N/A") -> -0.0022719278
A28: SHAREHOLDERS' FUND
A29: Stated capital | B29: 404245 | C29: 404245 | D29: =B29-C29 -> 0 | E29: =IF(C29<>0,(B29-C29)/ABS(C29),"N/A") -> 0
A30: Retained earnings | B30: 1193037 | C30: 1161085 | D30: =B30-C30 -> 31952 | E30: =IF(C30<>0,(B30-C30)/ABS(C30),"N/A") -> 0.027519088
A31: Revaluation reserve | B31: 505250 | C31: 505250 | D31: =B31-C31 -> 0 | E31: =IF(C31<>0,(B31-C31)/ABS(C31),"N/A") -> 0
A32: Statutory reserve | B32: 550928 | C32: 511919 | D32: =B32-C32 -> 39009 | E32: =IF(C32<>0,(B32-C32)/ABS(C32),"N/A") -> 0.076201508
A33: Total shareholders' fund | B33: 2653460 | C33: 2582499 | D33: =B33-C33 -> 70961 | E33: =IF(C33<>0,(B33-C33)/ABS(C33),"N/A") -> 0.027477649
A35: Total liabilities and shareholders' fund | B35: 10623681 | C35: 10570869 | D35: =B35-C35 -> 52812 | E35: =IF(C35<>0,(B35-C35)/ABS(C35),"N/A") -> 0.0049959942
A37: BALANCE SHEET INTEGRITY CHECK
A38: Period | B38: Total Assets | C38: Total Liabilities + Equity | D38: Difference | E38: Status
A39: 2026 | B39: =B16 -> 10623681 | C39: =B26+B33 -> 10623681 | D39: =B39-C39 -> 0 | E39: =IF(ABS(D39)<1,"✓ Balanced","✗ ERROR") -> ✓ Balanced
A40: 2025 | B40: =C16 -> 10570869 | C40: =C26+C33 -> 10570869 | D40: =B40-C40 -> 0 | E40: =IF(ABS(D40)<1,"✓ Balanced","✗ ERROR") -> ✓ Balanced

Sheet Ratio_Analysis
A1: Societe Generale Ghana PLC — Ratio Analysis
A2: Key Banking Ratios | Q1 2026 vs Q1 2025 | Figures sourced from Income_Statement and Balance_Sheet tabs
A4: KPI | B4: Formula | C4: Q1 2026 | D4: Q1 2025 | E4: Change | F4: Direction
A5: Net Interest Margin (NIM) | B5: Net Interest Income / Total Assets | C5: =Income_Statement!B7/Balance_Sheet!B16 -> 0.021161215 | D5: =Income_Statement!C7/Balance_Sheet!C16 -> 0.028854392 | E5: =C5-D5 -> -0.007693177 | F5: =IF(C5>D5,"▲ Improved","▼ Deteriorated") -> ▼ Deteriorated
A6: Cost-to-Income Ratio | B6: ABS(Total Operating Expenses) / Operating Income | C6: =ABS(Income_Statement!B26)/Income_Statement!B18 -> 0.63889443 | D6: =ABS(Income_Statement!C26)/Income_Statement!C18 -> 0.47144699 | E6: =C6-D6 -> 0.16744745 | F6: =IF(C6<D6,"▲ Improved","▼ Deteriorated") -> ▼ Deteriorated
A7: Return on Assets (ROA) | B7: Profit After Tax / Total Assets | C7: =Income_Statement!B30/Balance_Sheet!B16 -> 0.0048650745 | D7: =Income_Statement!C30/Balance_Sheet!C16 -> 0.012923914 | E7: =C7-D7 -> -0.0080588393 | F7: =IF(C7>D7,"▲ Improved","▼ Deteriorated") -> ▼ Deteriorated
A8: Return on Equity (ROE) | B8: Profit After Tax / Total Shareholders' Fund | C8: =Income_Statement!B30/Balance_Sheet!B33 -> 0.019478341 | D8: =Income_Statement!C30/Balance_Sheet!C33 -> 0.052901085 | E8: =C8-D8 -> -0.033422744 | F8: =IF(C8>D8,"▲ Improved","▼ Deteriorated") -> ▼ Deteriorated
A9: Loan-to-Deposit Ratio (LDR) | B9: Loans & Advances to Customers / Deposits from Customers | C9: =Balance_Sheet!B9/Balance_Sheet!B21 -> 0.62751207 | D9: =Balance_Sheet!C9/Balance_Sheet!C21 -> 0.74754475 | E9: =C9-D9 -> -0.12003268 | F9: =IF(C9>D9,"▲ Improved","▼ Deteriorated") -> ▼ Deteriorated
A10: Equity-to-Assets Ratio | B10: Total Shareholders' Fund / Total Assets | C10: =Balance_Sheet!B33/Balance_Sheet!B16 -> 0.24976842 | D10: =Balance_Sheet!C33/Balance_Sheet!C16 -> 0.24430338 | E10: =C10-D10 -> 0.0054650408 | F10: =IF(C10>D10,"▲ Improved","▼ Deteriorated") -> ▲ Improved
A11: Profit Before Tax Margin | B11: Profit Before Tax / Operating Income | C11: =Income_Statement!B28/Income_Statement!B18 -> 0.28427853 | D11: =Income_Statement!C28/Income_Statement!C18 -> 0.61184078 | E11: =C11-D11 -> -0.32756225 | F11: =IF(C11>D11,"▲ Improved","▼ Deteriorated") -> ▼ Deteriorated
A13: Note: ROA, ROE, and NIM are quarterly ratios (not annualised). Divide the quarterly P&L figure by the period-end balance sheet figure. All formulas link to the Income_Statement and Balance_Sheet tabs (green = cross-sheet reference).

Sheet Variance_Analysis
A1: Societe Generale Ghana PLC — Variance Analysis & Profit Bridge
A2: Profit Before Tax: Q1 2025 → Q1 2026 | Bridge Analysis | GH¢'000
A4: Driver | B4: Q1 2026 (GH¢'000) | C4: Q1 2025 (GH¢'000) | D4: GH¢ Impact on PBT | E4: Commentary
A5: Starting PBT (Q1 2025) | D5: =Income_Statement!C28 -> 212611 | E5: Baseline profit before tax
A6: Change in Net Interest Income | B6: =Income_Statement!B7 -> 224810 | C6: =Income_Statement!C7 -> 305016 | D6: =B6-C6 -> -80206 | E6: Core lending revenue — interest earned minus interest paid
A7: Change in Net Fees & Commission | B7: =Income_Statement!B11 -> 24824 | C7: =Income_Statement!C11 -> 23404 | D7: =B7-C7 -> 1420 | E7: Revenue from banking services and transaction fees
A8: Change in Total Other Op. Income | B8: =Income_Statement!B16 -> 25881 | C8: =Income_Statement!C16 -> 19074 | D8: =B8-C8 -> 6807 | E8: Trading revenue, fair value gains, other income
A9: Change in Impairment (net swing) | B9: =Income_Statement!B20 -> -21167 | C9: =Income_Statement!C20 -> 28942 | D9: =B9-C9 -> -50109 | E9: Swung from GH¢28,942k credit in 2025 to GH¢21,167k charge — total swing of GH¢50,109k
A10: Change in Personnel Expense | B10: =Income_Statement!B23 -> -76451 | C10: =Income_Statement!C23 -> -72465 | D10: =B10-C10 -> -3986 | E10: Staff costs — salaries, benefits, and related charges
A11: Change in Depreciation & Amort. | B11: =Income_Statement!B24 -> -38512 | C11: =Income_Statement!C24 -> -28758 | D11: =B11-C11 -> -9754 | E11: Fastest-growing cost line in percentage terms (+33.9%)
A12: Change in Other Operating Exp. | B12: =Income_Statement!B25 -> -61062 | C12: =Income_Statement!C25 -> -62602 | D12: =B12-C12 -> 1540 | E12: Admin, technology, occupancy, and other overhead costs
A13: Total Change in PBT (should equal Q1 2026 PBT − Q1 2025 PBT) | D13: =D6+D7+D8+D9+D10+D11+D12 -> -134288 | E13: =IF(ABS(D13-(Income_Statement!B28-Income_Statement!C28))<1,"✓ Bridge balances","✗ Check formulas") -> ✓ Bridge balances
A14: Ending PBT (Q1 2026) — cross-check | D14: =D5+D13 -> 78323 | E14: =IF(ABS(D14-Income_Statement!B28)<1,"✓ Matches IS","✗ Check") -> ✓ Matches IS
A16: TOP 3 DRIVERS OF PROFIT DECLINE (by absolute GH¢ impact)
A17: Rank | B17: Driver | C17: GH¢ Impact (000) | D17: % of Total Decline | E17: Assessment
A18: 1 | B18: Decline in Net Interest Income | C18: -80206 | D18: 0.597 | E18: STRUCTURAL — Interest income fell GH¢86,464k while rates and/or loan volumes declined
A19: 2 | B19: Impairment swing (credit → charge) | C19: -50109 | D19: 0.373 | E19: SIGNIFICANT — A GH¢28,942k release in 2025 swung to a GH¢21,167k charge in 2026
A20: 3 | B20: Rise in Depreciation & Amortisation | C20: -9754 | D20: 0.073 | E20: MODERATE — Fastest-growing cost line at 33.9% YoY; likely driven by asset investment

Sheet Business_Questions
A1: Societe Generale Ghana PLC — Business Questions: Model Answers
A2: All answers are sourced from the Income_Statement, Balance_Sheet, Ratio_Analysis, and Variance_Analysis tabs. Figures in GH¢'000.
A4: # | B4: Business Question | C4: Model Answer
A5: 1 | B5: What was the YoY change (GH¢ and %) in net interest income, and what does this suggest? | C5: Net interest income fell from GH¢305,016k to GH¢224,810k — a decline of GH¢80,206k or (26.3%). This indicates that the bank's core lending revenue contracted significantly, likely driven by a combination of lower interest rates on loans (reflecting monetary policy easing), reduced loan book volume (loans fell from GH¢4,817,070k to GH¢4,183,532k), or a mix shift toward lower-yielding assets. This is the single largest driver of the profit decline.
A6: 2 | B6: How did operating income change YoY, and which revenue line contributed most to the decline? | C6: Operating income fell from GH¢347,494k to GH¢275,515k — a decline of GH¢71,979k or (20.7%). Net interest income was the dominant driver, contributing GH¢80,206k of negative variance. This was partially offset by improved net fees and commission income (+GH¢1,420k) and stronger other operating income (+GH¢6,807k).
A7: 3 | B7: The impairment line swung from +GH¢28,942k (2025) to (GH¢21,167k) (2026). What does this mean and how much did it affect profitability? | C7: In Q1 2025, the bank released provisions — it had over-reserved for bad loans in prior periods and reversed GH¢28,942k back into profit (a credit). In Q1 2026, the bank charged GH¢21,167k in new provisions — increasing its reserves against loans expected to go bad. The total swing was GH¢50,109k — from a +GH¢28,942k profit boost to a (GH¢21,167k) profit drag. This is the second-largest driver of the YoY profit decline and signals a deterioration in credit quality.
A8: 4 | B8: Did total operating expenses rise or fall YoY? Which cost line drove the change? | C8: Total operating expenses rose from GH¢163,825k to GH¢176,025k — an increase of GH¢12,200k or 7.4%. The largest driver was depreciation and amortisation, which rose from GH¢28,758k to GH¢38,512k — an increase of GH¢9,754k or 33.9%. This is the fastest-growing cost line and suggests significant capital investment in assets (technology, branches, or equipment) whose depreciation is now flowing through the P&L.
A9: 5 | B9: What was the Net Interest Margin (NIM) in Q1 2026 vs Q1 2025? | C9: Q1 2026 NIM: GH¢224,810k / GH¢10,623,681k = 2.12% (quarterly). Q1 2025 NIM: GH¢305,016k / GH¢10,570,869k = 2.89% (quarterly). The NIM declined by 0.77 percentage points — meaning the bank earns less net interest income per cedi of assets deployed. This reflects the combination of falling interest income and a shift in the asset mix toward debt instruments (which may carry lower yields than customer loans).
A10: 6 | B10: What was the cost-to-income ratio in both periods? Is the bank becoming more or less efficient? | C10: Q1 2026: GH¢176,025k / GH¢275,515k = 63.9%. Q1 2025: GH¢163,825k / GH¢347,494k = 47.1%. The ratio rose by 16.8 percentage points — a significant deterioration in efficiency. In 2025, the bank spent 47 pesewas to earn one cedi of income. In 2026, it spent 64 pesewas. The bank is becoming meaningfully less efficient, driven by declining revenue rather than runaway cost growth.
A11: 7 | B11: What was the Return on Assets (ROA) and Return on Equity (ROE) for Q1 2026 vs Q1 2025? | C11: ROA — Q1 2026: GH¢51,685k / GH¢10,623,681k = 0.49% (quarterly). Q1 2025: GH¢136,617k / GH¢10,570,869k = 1.29% (quarterly). ROE — Q1 2026: GH¢51,685k / GH¢2,653,460k = 1.95% (quarterly). Q1 2025: GH¢136,617k / GH¢2,582,499k = 5.29% (quarterly). Both ratios deteriorated sharply, reflecting the significant drop in profitability against a broadly stable asset and equity base.
A12: 8 | B12: How did the loan-to-deposit ratio change YoY? What does this suggest? | C12: LDR Q1 2026: GH¢4,183,532k / GH¢6,666,855k = 62.8%. LDR Q1 2025: GH¢4,817,070k / GH¢6,443,855k = 74.8%. The ratio fell 12 percentage points, meaning the bank deployed proportionally less of its deposit base into loans. This suggests either a deliberate reduction in lending risk appetite or a shift in asset allocation — supported by the concurrent rise in debt instruments at amortised cost from GH¢1,396,566k to GH¢2,615,737k (likely government securities). While this reduces credit risk, it may further suppress NIM if those instruments carry lower yields.
A13: 9 | B13: What is the equity-to-assets ratio and how does it compare between 2026 and 2025? | C13: Q1 2026: GH¢2,653,460k / GH¢10,623,681k = 25.0%. Q1 2025: GH¢2,582,499k / GH¢10,570,869k = 24.4%. The ratio improved marginally (+0.6pp), reflecting slight equity growth (from retained earnings) against a broadly flat total asset base. The bank remains well-capitalised relative to its asset base.
A14: 10 | B14: Summarise in three sentences: what are the most important things the board needs to understand about Q1 2026 performance? | C14: Profit before tax fell 63.2% YoY from GH¢212,611k to GH¢78,323k, driven primarily by a GH¢80,206k decline in net interest income and a GH¢50,109k swing in the impairment charge from a 2025 credit to a 2026 provision charge. The bank's cost-to-income ratio deteriorated sharply from 47.1% to 63.9%, not because costs spiralled but because income fell much faster — making efficiency improvement contingent on revenue recovery rather than further cost-cutting. The balance sheet remains stable with improving capitalisation, but the shift away from loans toward government securities signals a more conservative lending posture that may constrain NIM recovery in Q2 2026.

Sheet Executive_Summary
A1: Societe Generale Ghana PLC — Executive Summary: Q1 2026 Financial Performance
A2: Prepared by: Junior Financial Analyst Intern | FP&A Department | For: Nana Kofi Asare-Mensah, Head of FP&A | Date: Q1 2026
A4: KPI SCORECARD — Q1 2026 vs Q1 2025
A5: KPI | B5: Q1 2026 | C5: Q1 2025 | D5: Change | E5: Signal
A6: Net Interest Margin (NIM) | B6: =Ratio_Analysis!C5 -> 0.021161215 | C6: =Ratio_Analysis!D5 -> 0.028854392 | D6: =B6-C6 -> -0.007693177 | E6: =IF(B6>C6,"🟢 Improved","🔴 Deteriorated") -> 🔴 Deteriorated
A7: Cost-to-Income Ratio | B7: =Ratio_Analysis!C6 -> 0.63889443 | C7: =Ratio_Analysis!D6 -> 0.47144699 | D7: =B7-C7 -> 0.16744745 | E7: =IF(B7<C7,"🟢 Improved","🔴 Deteriorated") -> 🔴 Deteriorated
A8: Return on Assets (ROA) | B8: =Ratio_Analysis!C7 -> 0.0048650745 | C8: =Ratio_Analysis!D7 -> 0.012923914 | D8: =B8-C8 -> -0.0080588393 | E8: =IF(B8>C8,"🟢 Improved","🔴 Deteriorated") -> 🔴 Deteriorated
A9: Return on Equity (ROE) | B9: =Ratio_Analysis!C8 -> 0.019478341 | C9: =Ratio_Analysis!D8 -> 0.052901085 | D9: =B9-C9 -> -0.033422744 | E9: =IF(B9>C9,"🟢 Improved","🔴 Deteriorated") -> 🔴 Deteriorated
A10: Loan-to-Deposit Ratio (LDR) | B10: =Ratio_Analysis!C9 -> 0.62751207 | C10: =Ratio_Analysis!D9 -> 0.74754475 | D10: =B10-C10 -> -0.12003268 | E10: "⚪ Neutral"
A11: Equity-to-Assets Ratio | B11: =Ratio_Analysis!C10 -> 0.24976842 | C11: =Ratio_Analysis!D10 -> 0.24430338 | D11: =B11-C11 -> 0.0054650408 | E11: =IF(B11>C11,"🟢 Improved","🔴 Deteriorated") -> 🟢 Improved
A12: Profit Before Tax Margin | B12: =Ratio_Analysis!C11 -> 0.28427853 | C12: =Ratio_Analysis!D11 -> 0.61184078 | D12: =B12-C12 -> -0.32756225 | E12: =IF(B12>C12,"🟢 Improved","🔴 Deteriorated") -> 🔴 Deteriorated
A15: TOP 3 FINDINGS
A16: 1 | B16: Net interest income fell GH¢80,206k (26.3%) — the single largest driver of the 63.2% profit decline, reflecting lower lending volumes and/or rates.
A17: 2 | B17: The impairment line swung GH¢50,109k (from a GH¢28,942k credit to a GH¢21,167k charge), signalling a deterioration in credit quality that requires close monitoring.
A18: 3 | B18: Cost-to-income ratio deteriorated from 47.1% to 63.9% — not from cost growth (+7.4%) but from a sharper revenue decline (−20.7%), making revenue recovery the priority.

Sheet CFO_Memo
A1: SOCIETE GENERALE GHANA PLC — CFO COMMENTARY MEMO
A3: TO:
A4: Nana Kofi Asare-Mensah, Head of Financial Planning and Analysis
A5: FROM:
A6: Junior Financial Analyst Intern, FP&A
A7: SUBJECT:
A8: Q1 2026 Financial Performance — Analysis for CFO Briefing
A9: DATE:
A10: May 2026
A12: PERFORMANCE SUMMARY
A13: Societe Generale Ghana PLC reported profit before tax of GH¢78,323k for Q1 2026, a decline of GH¢134,288k (63.2%) compared to GH¢212,611k in Q1 2025. Profit after tax fell from GH¢136,617k to GH¢51,685k, with earnings per share declining from GH¢0.77 to GH¢0.29. The performance was driven by a confluence of revenue contraction, a reversal of the prior-year impairment credit, and a modest rise in operating costs.
A15: KEY DRIVERS OF VARIANCE
... A26: Management should closely monitor three leading indicators in Q2 2026: the trajectory of net interest income (which will depend on whether lending volumes recover or monetary conditions shift further), the evolution of impairment charges (a second consecutive provision charge would confirm a systemic credit quality concern rather than a one-off), and the realisation of expected returns from the capital investments reflected in the rising depreciation line. Revenue recovery — not cost reduction — is the primary lever available to restore the profitability ratios to Q1 2025 levels.

Sheet Claude_Prompt_Log
A1: Claude AI Prompt Log — SG Ghana Q1 2026 Financial Analysis Internship
A2: Documents 6 example Claude AI prompts used during the internship. Students should replace these with their own actual prompts.
A4: # | B4: Prompt Used | C4: What It Helped Me Accomplish
A5: 1 | B5: Write an Excel formula to calculate the percentage change between two values where Q1 2026 is in column B and Q1 2025 is in column C. Handle the case where the prior period is zero. | C5: Helped me build the % Variance column on the Income_Statement and Balance_Sheet tabs with a formula that avoids #DIV/0! errors.
A6: 2 | B6: Define Net Interest Margin for a commercial bank and write the Excel formula. My net interest income is in Income_Statement tab cell B7. My total assets are in Balance_Sheet tab cell B16. I do not want to annualise — just the quarterly ratio. | C6: Helped me confirm the correct NIM definition (quarterly, not annualised) and write the cross-sheet Excel formula for the Ratio_Analysis tab.
A7: 3 | B7: The impairment line on Societe Generale Ghana's income statement moved from +GH¢28,942k in Q1 2025 to -GH¢21,167k in Q1 2026. Explain in plain language what this means for the bank and how to quantify the total impact on profit. | C7: Helped me understand the provision release vs provision charge concept and correctly calculate the GH¢50,109k total swing for the profit bridge and business question answers.
A8: 4 | B8: I have built a profit bridge table in Excel showing the GH¢ impact of each income statement line on the year-on-year change in profit before tax. My total driver sum is -134,200 but the actual PBT change is -134,288. What could explain the small difference and how should I validate the bridge? | C8: Helped me identify that I had rounded one line item and showed me how to add a bridge balance-check formula using IF and ABS to confirm the bridge reconciles.
A9: 5 | B9: I am building a waterfall chart in Excel to show a profit bridge from Q1 2025 to Q1 2026 for a Ghanaian bank. How do I structure the data range to create a waterfall in Excel, including the starting bar, positive bars, negative bars, and the ending bar? | C9: Helped me set up the stacked bar approach needed to simulate a waterfall chart in Excel, including how to format the invisible base series and colour the positive vs negative bars.
A10: 6 | B10: I am a junior financial analyst writing a CFO commentary memo for Societe Generale Ghana's Q1 2026 results. Here is my draft [pasted memo text]. Review it for professional tone, precision, and whether my interpretation of the cost-to-income deterioration is correct. | C10: Helped me refine the memo language, confirmed that my cost-to-income interpretation (revenue problem not cost problem) was analytically correct, and suggested stronger phrasing for the outlook section.
